[
  {
    "id": 1,
    "message": "ONT diperbarui: SD BOPKRI BINTARAN (LM001127) \u2192 SD BOPKRI BINTARANn (LM001127)",
    "type": "info",
    "timestamp": "2025-10-08T14:39:12.869080",
    "ont_id": 1,
    "ont_name": "SD BOPKRI BINTARANn",
    "read": true
  },
  {
    "id": 2,
    "message": "ONT diperbarui: SD BOPKRI BINTARANn (LM001127) \u2192 SD BOPKRI BINTARAN (LM001127)",
    "type": "info",
    "timestamp": "2025-10-08T14:39:28.130594",
    "ont_id": 1,
    "ont_name": "SD BOPKRI BINTARAN",
    "read": true
  },
  {
    "id": 3,
    "message": "ONT diperbarui: SD BOPKRI BINTARAN (LM001127) \u2192 SD BOPKRI BINTARAN (LM001127)",
    "type": "info",
    "timestamp": "2025-10-08T14:41:44.450636",
    "ont_id": 1,
    "ont_name": "SD BOPKRI BINTARAN",
    "read": true
  },
  {
    "id": 4,
    "message": "ONT diperbarui: SD BOPKRI BINTARAN (LM001127) \u2192 SD BOPKRI BINTARAN (LM001127)",
    "type": "info",
    "timestamp": "2025-10-08T14:42:44.075571",
    "ont_id": 1,
    "ont_name": "SD BOPKRI BINTARAN",
    "read": true
  },
  {
    "id": 5,
    "message": "ONT diperbarui: SD BOPKRI BINTARAN (LM001127) \u2192 SD BOPKRI BINTARAN (LM001127)",
    "type": "info",
    "timestamp": "2025-10-08T14:44:40.429980",
    "ont_id": 1,
    "ont_name": "SD BOPKRI BINTARAN",
    "read": true
  },
  {
    "id": 6,
    "message": "ONT baru ditambahkan: Carter Zimmerman (Et sequi velit veli)",
    "type": "success",
    "timestamp": "2025-10-08T14:50:29.650019",
    "ont_id": 226,
    "ont_name": "Carter Zimmerman",
    "read": false
  },
  {
    "id": 7,
    "message": "ONT diperbarui: Carter Zimmerman (Et sequi velit veli) \u2192 Server cacti (000000)",
    "type": "info",
    "timestamp": "2025-10-08T14:51:58.975166",
    "ont_id": 226,
    "ont_name": "Server cacti",
    "read": false
  },
  {
    "id": 8,
    "message": "ONT diperbarui: Server cacti (000000) \u2192 Server cacti (000000)",
    "type": "info",
    "timestamp": "2025-10-08T15:01:50.164990",
    "ont_id": 226,
    "ont_name": "Server cacti",
    "read": false
  },
  {
    "id": 9,
    "message": "ONT dihapus: Server cacti (000000)",
    "type": "warning",
    "timestamp": "2025-10-08T15:09:54.168178",
    "ont_id": 226,
    "ont_name": "Server cacti",
    "read": false
  }
]